distributed_tools/__init__.py
distributed_tools/functionTools.py
distributed_tools/redis_util.py
distributed_tools_bonc-0.1.2.dist-info/METADATA
distributed_tools_bonc-0.1.2.dist-info/WHEEL
distributed_tools_bonc-0.1.2.dist-info/top_level.txt
distributed_tools_bonc-0.1.2.dist-info/zip-safe
distributed_tools_bonc-0.1.2.dist-info/RECORD
